{"content":[{"address":null,"addressResolution":null,"altitude":"Unknown","city":"Kings Park","country":"United States","county":null,"created":null,"deleted":false,"description":"","detailedDescription":"At approximately 11:25 3 objects forming a triangle in flight pattern flew over kings park ny from the southwest to the northeast.  they were not like regular aircraft as they made no sound and were a glowing orange color - they were at a lower altitude as they were rather large.  they flew in a path like jets but glowed orange.  within 1 minute another group of two flew in the same direction as the first three - toward long ialand sound.","distance":"Over One Mile","duration":"","entityEncountered":false,"favorited":0,"features":"Unknown","flightPath":"Path with directional change","formattedAddress":null,"id":31497,"landingOccurred":false,"latitude":40.86902770218323,"location":null,"logNumber":"US-09042011-0001","longitude":-73.24795849239085,"occurred":1315117500000,"potentialRelations":[],"rating":"Unrated","region":"New York","reportedWeather":null,"shape":"Oval","source":"MUFON","status":null,"submitted":1315119767000,"summary":"5 glowing orange balls - like aircraft - 2 groups 3 and then 2","tags":["none"],"timeZone":null,"timeZoneName":"","tweeted":0,"urls":null,"weather":null,"zipcode":"11754","daysBetweenOccurrenceAndSubmission":0,"locationName":"Kings Park, New York","triangle":false,"type":"UFO Sighting","$$hashKey":"object:37363"},{"address":null,"addressResolution":null,"altitude":"Over 500 Feet (no cloudcover)","city":"Freehold Township","country":"United States","county":null,"created":null,"deleted":false,"description":"","detailedDescription":"I was camping out on monmouth battlefield state park with my unit at this years 2011 rev war reenactment of the battle of monmouth. i arrived with my family friday night and several people said to have seen a strange glowing object with no sound flying overhead but i didn't see it for i was in the bathroom at the time. plenty of witnesses to that sighting. saturday night\r\naround 10:50pm est i was outside talking with my commander when another member pointed out there is something in the sky. that is when i turned and looked up and could see a round disc that was glowing red/light pink with an aura of the same color around the edges (reminded me of the reentry of the space shuttle glowing from the burning plasma underneath. same color and aura effect.) no sound coming from it what so ever but could hear a passenger jet and see one flying in the distance away from where i was standing. this had no wings and i kept saying it looks like it might be entering our atmosphere or skipping off it. that is when i noticed it making a left turn and continue to fly out of sight. we all didn't know what it was but most laughed it off as a ufo. after that i kept an eye out for it and close to 20 minutes later it appeared again but this time seemed to be flying slower and had a slight zig-zag, wobble as it was turning and slowing down even more. same burning aura covering it and around it. again no sound. it flew the same flight path as before. knowing that an altitude of 120 km (75 mi) is where atmospheric effects become noticeable during atmospheric reentry of the space shuttle the disc appeared to be a about 2 centimeters radius. this tells me that this disc is huge that is entering our atmosphere.\r\n\r\nmy personal feelings at the sight were that of awe as well as investigative as to what it was i was seeing and taking account of others reactions to it as well to make sure i was not alone in seeing it. my whole family seen it too. when i seen the zig-zag wobble in the flightpath and slowing down i recalled the space shuttle doing the same to bleed off airspeed. there were was a couple fighter jets (f-16) flying in the direction of the disc's flight path 5 min after losing sight of the disc the second time flyby. \r\n\r\nthere were others that seen close to a hundred others around in their camps both british and continental that night.","distance":"Unknown","duration":"00:02:00","entityEncountered":false,"favorited":0,"features":"Unknown","flightPath":"Path with directional change,Other","formattedAddress":null,"id":31496,"landingOccurred":false,"latitude":40.2709842,"location":null,"logNumber":"US-09032011-0030","longitude":-74.3176876,"occurred":1308462600000,"potentialRelations":[],"rating":"Unrated","region":"New Jersey","reportedWeather":null,"shape":"Circle,   Disc","source":"MUFON","status":null,"submitted":1315118630000,"summary":"Glowing disc flying at high altitude glowing red like burning plasma underneath it with no sound what so ever from it.","tags":["disc","ufo"],"timeZone":null,"timeZoneName":"","tweeted":0,"urls":["http://www.mufoncms.com/files_jeud8334j/31496_submitter_file1__UnknownObject1.jpeg"],"weather":null,"zipcode":"07726","daysBetweenOccurrenceAndSubmission":77,"locationName":"Freehold Township, New Jersey","triangle":false,"type":"UFO Sighting","$$hashKey":"object:37364"},{"address":null,"addressResolution":null,"altitude":"Over 500 Feet (no cloudcover)","city":"Whittier","country":"United States","county":null,"created":null,"deleted":false,"description":"","detailedDescription":" driving on 60 fwy going east at 10:30 am on 9/3/11..Upon entrance to fwy while my husband drove i immediately noticed a large white square up high in the northern part of the sky, i often take pictures of clouds. i thought it was strange in the shape, square clouds are not the norm even though it looked like a cloud at first. it was a drive from rowan ave in east la to rowland hts.,,,the entire drive i had my eye up in the sky and my husband and 5 yr old son did also. i began to try to take a photo with both cameras i had just came from a baptism and had them ready. my husband was able to get a good look when we came to a mild traffic jam and then again when we exited on nogales. the shape had stopped and then started to move towards the foothills and soon disappeared from our viewpoint due to a large building. i did manage to snap some shots...It seemed to flutter at the top of the square and was plain white...???? i wanted to follow it some more and wasn't able to due to traffic..I would like to know what that was...\r\n ","distance":"Over 1 Mile, Unknown","duration":"01:00:00","entityEncountered":false,"favorited":0,"features":"None","flightPath":"Stationary","formattedAddress":null,"id":31495,"landingOccurred":false,"latitude":33.9811793,"location":null,"logNumber":"US-09032011-0029","longitude":-118.031414,"occurred":1315071600000,"potentialRelations":[],"rating":"Unrated","region":"California","reportedWeather":null,"shape":"Square,   Rectagular","source":"MUFON","status":null,"submitted":1315118498000,"summary":"White large square shaped object in sky","tags":["none"],"timeZone":null,"timeZoneName":"","tweeted":0,"urls":["http://www.mufoncms.com/files_jeud8334j/31495_submitter_file1__ufo003.jpg","http://www.mufoncms.com/files_jeud8334j/31495_submitter_file2__ufo005.jpg","http://www.mufoncms.com/files_jeud8334j/31495_submitter_file3__ufo002.jpg"],"weather":null,"zipcode":"0","daysBetweenOccurrenceAndSubmission":0,"locationName":"Whittier, California","triangle":false,"type":"UFO Sighting","$$hashKey":"object:37365"},{"address":null,"addressResolution":null,"altitude":"Over 500 Feet (no cloudcover)","city":"Las Vegas","country":"United States","county":null,"created":null,"deleted":false,"description":"","detailedDescription":"My fiance and i have been seeing a ton of ufo's lately over las vegas (see the mufon report i made previously: http://mufoncms.Com/cgi-bin/report_handler.Pl?Req=view_long_desc&id=31351&rnd= )\r\n\r\ndue to the recent sightings we decided to go out to red rock canyon, located about 5 miles west of the edge of las vegas.  there are absolutely no lights anywhere around the canyon, so it's perfect for star-gazing.  we arrived around 3am and we couldn't have been outside of our car for more than 5-10 minutes when we noticed a ufo flying towards us from the west heading towards the east.  the object would move from side-to-side zig-zagging it's way towards us until it stopped and hovered.  this amazing object was very bright and it flickered every color in the rainbow.  the colors were extremely vivid and it changed colors extremely rapidly.  we couldn't see this from the ground when we were watching it, but after reviewing the video we noticed a smaller light located at first to the bottom-left of the ufo, and then to the top-right of the ufo, that would randomly blink on.  this tiny object seems to be located at a fixed distance to the main multi-colored ufo, however it only appears in a small portion of the recorded video.\r\n\r\nyou can view the video in 1080p hd on youtube at this url: http://www.Youtube.Com/watch?V=za0lyuev7aw \r\n\r\ni've also attached a few screen caps of the ufo to this report.","distance":"Over 1 Mile, Unknown","duration":"","entityEncountered":false,"favorited":0,"features":"Unknown","flightPath":"Hovering then path,Path with directional change,Path then hovering","formattedAddress":null,"id":31493,"landingOccurred":false,"latitude":36.14508771600099,"location":null,"logNumber":"US-09032011-0027","longitude":-115.42399690404903,"occurred":1314860400000,"potentialRelations":[],"rating":"Unrated","region":"Nevada","reportedWeather":null,"shape":"Star-like","source":"MUFON","status":null,"submitted":1315115794000,"summary":"On video: multi-colored ufo moving and hovering west of las vegas","tags":["lights","ufo","video"],"timeZone":null,"timeZoneName":"","tweeted":0,"urls":["http://www.mufoncms.com/files_jeud8334j/31493_submitter_file1__Multi-Colored-UFO-1.png","http://www.mufoncms.com/files_jeud8334j/31493_submitter_file2__Multi-Colored-UFO-2.png","http://www.mufoncms.com/files_jeud8334j/31493_submitter_file3__Multi-Colored-UFO-3.png"],"weather":null,"zipcode":"89124","daysBetweenOccurrenceAndSubmission":2,"locationName":"Las Vegas, Nevada","triangle":false,"type":"UFO Sighting","$$hashKey":"object:37366"},{"address":null,"addressResolution":null,"altitude":"Unknown","city":"Cudjoe Key","country":"United States","county":null,"created":null,"deleted":false,"description":"","detailedDescription":"Lower sugarloaf florida keys. red/orange ball heads from sw ocean side to nw gulf side. no noise. did not blink like plane. object sparkled. ascended straight up then gone. lasted 3 mins.\r\n\r\n","distance":"Unknown","duration":"00:03:00","entityEncountered":false,"favorited":0,"features":"","flightPath":"Path with directional change","formattedAddress":null,"id":31492,"landingOccurred":false,"latitude":24.6865905,"location":null,"logNumber":"US-09032011-0026","longitude":-81.4937993,"occurred":1315105380000,"potentialRelations":[],"rating":"Unrated","region":"Florida","reportedWeather":null,"shape":"Fireball","source":"MUFON","status":null,"submitted":1315114834000,"summary":"Red ball glowing ball ascends into the air ","tags":["none"],"timeZone":null,"timeZoneName":"","tweeted":0,"urls":null,"weather":null,"zipcode":"33042","daysBetweenOccurrenceAndSubmission":0,"locationName":"Cudjoe Key, Florida","triangle":false,"type":"UFO Sighting","$$hashKey":"object:37367"},{"address":null,"addressResolution":null,"altitude":"Landed","city":"Sturgis","country":"United States","county":null,"created":null,"deleted":false,"description":"","detailedDescription":"To many to tell need to contact me. we we not to far from ellsworth airforce base. plenty to tell you to much to recall on this form.","distance":"21-100 Feet, 101-500 Feet","duration":"","entityEncountered":false,"favorited":0,"features":"Other","flightPath":"Stationary,Hovering then path,Straight-line path","formattedAddress":null,"id":31491,"landingOccurred":false,"latitude":44.39852604729841,"location":null,"logNumber":"US-09032011-0025","longitude":-103.4826152976923,"occurred":-189273600000,"potentialRelations":[],"rating":"Unrated","region":"South Dakota","reportedWeather":null,"shape":"Circle,   Flash,   Star-like","source":"MUFON","status":null,"submitted":1315111765000,"summary":"Trust me during the late 60s early 70s i watched multiple ufo sightings in sturgis and rapid citysd","tags":["contact"],"timeZone":null,"timeZoneName":"","tweeted":0,"urls":null,"weather":null,"zipcode":"57785","daysBetweenOccurrenceAndSubmission":17411,"locationName":"Sturgis, South Dakota","triangle":false,"type":"UFO Sighting","$$hashKey":"object:37368"},{"address":null,"addressResolution":null,"altitude":"Unknown","city":"New Rochelle","country":"United States","county":null,"created":null,"deleted":false,"description":"","detailedDescription":"Long time back as i was teaching on the natural sciences some how i was interrupted by some unknown force to add clairty to my subject matter which was ethnics and human values at the college of new rochelle, ny\r\nplease take it for whta it is do not ontact me as i will deny this?","distance":"Unknown","duration":"","entityEncountered":false,"favorited":0,"features":"","flightPath":"","formattedAddress":null,"id":31489,"landingOccurred":false,"latitude":40.9175382,"location":null,"logNumber":"US-09032011-0024","longitude":-73.7766549,"occurred":769330800000,"potentialRelations":[],"rating":"Unrated","region":"New York","reportedWeather":null,"shape":"Unknown","source":"MUFON","status":null,"submitted":1315108510000,"summary":"X-files","tags":["none"],"timeZone":null,"timeZoneName":"","tweeted":0,"urls":["http://www.mufoncms.com/files_jeud8334j/31489_submitter_file1__??_and_773_and_8722V_2??^FX-FILE.jnt"],"weather":null,"zipcode":"0","daysBetweenOccurrenceAndSubmission":6316,"locationName":"New Rochelle, New York","triangle":false,"type":"UFO Sighting","$$hashKey":"object:37369"},{"address":null,"addressResolution":null,"altitude":"Over 500 Feet (no cloudcover)","city":"Breckenridge","country":"United States","county":null,"created":null,"deleted":false,"description":"","detailedDescription":"1st sitting: july of 2002. from living room of house at 10,600 ft. asl. sitting on couch looking through windows at the peaks of mountains (ski areas) above breckenridge, co. was looking out at peak 9 and 10 (from emmet lodge rd) and noticed a 'huge' submarine like object hovering (stationary) between the 2 peaks on the west side of breck. it wasn't moving at all. metallic dull grey in color and could only see the 'front' of the object, but because of the 'nose' of the object it was easy to assess that it was an actual 'nose/front' of a very large cylindrical object having no wings or other extended phalanges of any kind. it stayed there for at least 2 hrs. totally motionless (i did not report it or mention it to anyone).\r\n\r\n2nd. sitting: nov. 18th. 2008 about 3:15 am. observed from new residence in blue river (10,240 ft asl) just south of breckenridge on rt.#9. was up late that night and lounging on the couch while reading. after, turning out the lights and just relaxing in the dark while looking out at the many, many astonishing stars on a clear unobstructed night noticed 'one' particular star (at least it looked like a star, but i could not tell how distant it was although it looked like a star among the others) began to expand its countenance so-to-speak. it caught my eye and i was fixed on it. now, you know how in movie films the camera man zooms in on a shot of a particular object or person -- as in really quick spaced steps? you know, how the object through 2 or 3 really fast and deliberate steps zooms closer to you and immediately takes place and the object or person is immediately in your face as you are viewing the movie? well, that is exactly what happened: with only about 3 or 4 immediate 'zoom steps' towards me the object presented itself and then abruptly stopped over the mountain my house faces just above the trees. it was absolutely amazingly beautiful...A spherical shaped (flying saucer type) with windows all around...Like a mouth piece on harmonica's face (spaces for placing the mouth over to give out harmonics). the 'harmonica's face/windows' from what i could see were faint but noticeable and well defined, filled with radiant white-gold light and also wrapped in a beautiful and brilliant golden white light that almost concealed the object in its stunning auric glow. yet, as i said it was quite view-able and defined in its saucer shaping. it was about 1/2  or 3/4's of a mile above me as it hovered over the tree tops of the mountain where my house faces. it hovered there for about 20 seconds or so in brilliant array as if showing itself off in all its splendor--no, there was no inward revolving of the 'windows' from what i could observe.However, the up and bottom borders of the windows did look as if they were revolving. no other lights than what i have described. it was about the size (from that distant) of about 2 football fields. then it backed up at a 90 degree angle, i.E. lifting it's back end up as if the 'harmonica type face/windows' were pointing directly down toward the trees. again, with the windows pointing down...It backed upward - paused for a brief second and then descended instantly behind the mountain. it was absolutely incredible.\r\n\r\nsitting # 3: this just took place the other night about 2:30 am. the stars were visible on a clear night. it seemed like ten's of thousands of them were out and there was a lot of commercial plane activity as well. all of a sudden from the same directions of dia (denver international airport)an object shaped just like the space shuttle flying-more like gliding at such a perfect hypnotizing-gliding type of speed. it was positively stunning in its flight pattern. just gingerly gliding only about a mile or so above the mountain that my house faces with commercial airline planes flying miles and miles above it. the entire object was shaped exactly like the nasa space module except for one thing: the entire object was pure white-yellow light...That's correct; the entire object was entirely light shaped just like the nasa space module and about 3 to 5 x's the nasa space module's size by my visual observation and subjective assessment as to measures.Yet, clear enough all the same! the observation took about 30 seconds as it passed over the mountain--my house and the mountains on the other side of where i reside (mount quandry) and continued 'gliding' at that pure and perfect pace--looking absolutely care-free and chilling out. like the other two sittings there were no sounds. of course, being in colorado one has to wonder whether it is 'our's or 'extra-terrestrial' because of the government bases in the area. \r\n\r\nnote: in the last two weeks there have been some very strange occurrences in the night skies taking place above where i reside. just early this morning around 2 a.M.: as i was looking out the window toward the skies there was a very brief projection of a lighted object of which shape i cannot describe. it took place so fast and unexpected, yet visible enough for my eyes to catch it. it wasn't lightning or a comet (shooting star) albeit...About an hour later i did notice a comet flashing by. another, occurrence that took place two nights in succession about 1 am where there was much cloud covering because of storms were flashes of lights in sequence order of motion with triangular shapes beside one another totaling 4 in a row equal distant apart from one another. they flashed two times as if there were moving behind the clouds. now, whether these last two occurrences i am posting are storm phenomena of some type...I cannot say for sure. however, as far as the 3 sittings mentioned above i have described them as best i could. why i have been 'fortunate' or just in the right place at the right time to observe these objects--i can't say, because i would think it unusually to see 3 different ufo's over a period of 8 years...At least i think so!","distance":"501 Feet - 1 Mile, Over 1 Mile","duration":"","entityEncountered":false,"favorited":0,"features":"","flightPath":"Stationary,Hovering then path","formattedAddress":null,"id":31488,"landingOccurred":false,"latitude":39.4886837,"location":null,"logNumber":"US-09032011-0023","longitude":-106.0303318,"occurred":1314946800000,"potentialRelations":[],"rating":"Unrated","region":"Colorado","reportedWeather":null,"shape":"Blimp,   Cigar,   Disc,   Sphere","source":"MUFON","status":null,"submitted":1315108405000,"summary":"Three sittings over 9 years....See below for details","tags":["none"],"timeZone":null,"timeZoneName":"","tweeted":0,"urls":null,"weather":null,"zipcode":"80424","daysBetweenOccurrenceAndSubmission":1,"locationName":"Breckenridge, Colorado","triangle":false,"type":"UFO Sighting","$$hashKey":"object:37370"},{"address":null,"addressResolution":null,"altitude":"Unknown","city":"Richmond","country":"United States","county":null,"created":null,"deleted":false,"description":"","detailedDescription":"I went out to my front yard to take some beautiful pictures of tropical storm lee as it appeared from our hometown richmond,texas.I took several photos of the clouds and came back inside to download them onto my computer.In one of the pictures i noticed a really small object that was highlighted against the white storm clouds.I zoomed in on this object as was amazed at what i had caught by accident!!!It is a red round disc flared out on the bottom with what looks like some sort of antenneas on top.I did not see this by eye as i was taking the photo.I just saw it on my computer.I don't even know if it was visible to my eye in the light spectrum i can see.I don't know what it was,but i know it was not an airplane and was not supposed to be where it was.I only hope someone can help tell me what this object was or is.","distance":"Unknown","duration":"","entityEncountered":false,"favorited":0,"features":"Other","flightPath":"Stationary","formattedAddress":null,"id":31486,"landingOccurred":false,"latitude":29.58507345959882,"location":null,"logNumber":"US-09032011-0022","longitude":-95.74489290613131,"occurred":1315062900000,"potentialRelations":[],"rating":"Unrated","region":"Texas","reportedWeather":null,"shape":"Disc","source":"MUFON","status":null,"submitted":1315106653000,"summary":"Red disc in photo of tropical storm lee as seen from richmond","tags":["disc","photo"],"timeZone":null,"timeZoneName":"","tweeted":0,"urls":["http://www.mufoncms.com/files_jeud8334j/31486_submitter_file1__DSC00387.JPG","http://www.mufoncms.com/files_jeud8334j/31486_submitter_file2__DSC00385.JPG","http://www.mufoncms.com/files_jeud8334j/31486_submitter_file3__DSC00386.JPG"],"weather":null,"zipcode":"77469","daysBetweenOccurrenceAndSubmission":0,"locationName":"Richmond, Texas","triangle":false,"type":"UFO Sighting","$$hashKey":"object:37371"},{"address":null,"addressResolution":null,"altitude":"Landed","city":"Barnegat Township","country":"United States","county":null,"created":null,"deleted":false,"description":"","detailedDescription":"I was walking my dog about 9pm when i first noticed what i thought was a star it was rapidly changing colors, then off to the left of that object a bright ball of light appeared i watched as it slowly decended down into the woods and began flashing a white light. i've tried to come up with a logical explaination, but i cant. every night since i saw this happen i have returned to the spot, so far the flashing light is still out there, it has been 7 days now.  \r\n\r\n","distance":"Unknown","duration":"","entityEncountered":false,"favorited":0,"features":"Unknown","flightPath":"Hovering then path","formattedAddress":null,"id":31485,"landingOccurred":false,"latitude":39.7649223,"location":null,"logNumber":"US-09032011-0021","longitude":-74.2693297,"occurred":1314514800000,"potentialRelations":[],"rating":"Unrated","region":"New Jersey","reportedWeather":null,"shape":"Other","source":"MUFON","status":null,"submitted":1315106788000,"summary":"A bright light appeared in sky, then desended and began flashing.","tags":["flash","light"],"timeZone":null,"timeZoneName":"","tweeted":0,"urls":null,"weather":null,"zipcode":"08005","daysBetweenOccurrenceAndSubmission":6,"locationName":"Barnegat Township, New Jersey","triangle":false,"type":"UFO Sighting","$$hashKey":"object:37372"},{"address":null,"addressResolution":null,"altitude":"Over 500 Feet (no cloudcover)","city":"Los Angeles","country":"United States","county":null,"created":null,"deleted":false,"description":"","detailedDescription":"I was sitting in my friends yard and looked up at the sky for no real reason and at the end of his yard, 25 feet from where i am sitting, he has a couple of very tall palm trees.  just above the palm trees i see 3 lights moving together in a straight line.  the first light was large and had a kind of peach-colored aura.  it stopped and the other two lights, smaller, the size and look of maybe the north star, zoomed into it and then it disappeared.  i was too shocked to say anything the first moment i saw it, but when i did say something, my friends were mid conversation and ignored me and so they missed it. it was a bright summer evening and there was nothing else in the sky as far as i could remember.  there was a small cloud formation a few inches away from the brightest light.  i have the exact date marked in my diary, but i don't have that on me right now, i do know that it was a recent sunday, however.","distance":"Unknown","duration":"00:00:02","entityEncountered":false,"favorited":0,"features":"None","flightPath":"Straight-line path,Path then hovering","formattedAddress":null,"id":31484,"landingOccurred":false,"latitude":34.1975405,"location":null,"logNumber":"US-09032011-0020","longitude":-118.472196,"occurred":1310954400000,"potentialRelations":[],"rating":"Unrated","region":"California","reportedWeather":null,"shape":"Circle,   Star-like","source":"MUFON","status":null,"submitted":1315105733000,"summary":"Three lights, one bright and large, hover and two small lights absorbed and dissappears","tags":["lights"],"timeZone":null,"timeZoneName":"","tweeted":0,"urls":["http://www.mufoncms.com/files_jeud8334j/31484_submitter_file1__ufoatjohnshouse.jpg"],"weather":null,"zipcode":"91416","daysBetweenOccurrenceAndSubmission":48,"locationName":"Los Angeles, California","triangle":false,"type":"UFO Sighting","$$hashKey":"object:37373"},{"address":null,"addressResolution":null,"altitude":"Over 500 Feet (no cloudcover)","city":"Redlands","country":"United States","county":null,"created":null,"deleted":false,"description":"","detailedDescription":"On october 31st in the year 1999 or 2000, three friends and i were in the car on our way to a halloween party in redlands, california around 9pm. \r\nmy friend was looking for a place to park and i was looking at the moon because it was full that night. then i spotted what i thought at first was a falling star. i told my friends to look at the falling star. we all stopped and watched from the car as the star suddenly came to an abrupt stop. \r\nat that moment our ooos and awws became gasps of confusion and shock as we watched the star make a precise triangular maneuver. i was still confused as to what i was now looking at because i knew it was no longer a falling star. i remember one friend saying, \"it's a ufo, it's a ufo\" repeating himself in astonishment. i now couldn't believe what i was seeing. the starlight then starting moving north at about 500 mph and started a blinking light pattern with different colors. red being one of the colors i remember for sure.\r\nafter the blinking light pattern, it then appeared to charge up with an extremely pure white light and then shot off unbelievably fast. in the blink of an eye, it was gone. \r\ni was then convinced that yes, as my friend had said, it was a ufo. i was in shock, but also felt really lucky to have witnessed such a phenomenon. i had never seen anything like that before and till this day, as i search countless on-line videos clamming to be footage of ufos, i still have not come across anything that looks like what i saw. \r\nthe ufo's lights were so pure and bright, i've only seen light like that in stars and no aircraft that i know of as a civilian goes way past mach 10 or at the speed of light. ","distance":"Over One Mile","duration":"00:00:10","entityEncountered":false,"favorited":0,"features":"Unknown","flightPath":"Stationary,Straight-line path,Path with directional change,Other","formattedAddress":null,"id":31483,"landingOccurred":false,"latitude":34.0615393,"location":null,"logNumber":"US-09032011-0019","longitude":-117.1781381,"occurred":972979200000,"potentialRelations":[],"rating":"Unrated","region":"California","reportedWeather":null,"shape":"Star-like","source":"MUFON","status":null,"submitted":1315104384000,"summary":"Ufo seen over redlands , ca in 1999 or 2000 looked like a rapidly moving star. ","tags":["ufo"],"timeZone":null,"timeZoneName":"","tweeted":0,"urls":["http://www.mufoncms.com/files_jeud8334j/31483_submitter_file1__UFO_re_enactment.mov"],"weather":null,"zipcode":"0","daysBetweenOccurrenceAndSubmission":3959,"locationName":"Redlands, California","triangle":false,"type":"UFO Sighting","$$hashKey":"object:37374"},{"address":null,"addressResolution":null,"altitude":"Over 500 Feet (under cloudcover)","city":"Bucaramanga","country":"Colombia","county":null,"created":null,"deleted":false,"description":"","detailedDescription":"I am with my frind because i sell my older photo camera a nikon d5000 and we are testing the camera and the tripod y gave to him we put the camera on the tripod and we turn on the camera in auto mode my friend and i seen some lights over the ruitoque  mountain my frinend action the shutter of the camera and we have a picture of the event the lights disapear in the same way that they appear . i am a profesional videographer and photograph , ans we analize the photo many times ans the read in photoshop tell us that its a solid object in the photo we are send you the case and the file for your review ......\r\n\r\n\r\nmy best regards","distance":"Unknown","duration":"","entityEncountered":false,"favorited":0,"features":"None","flightPath":"Stationary","formattedAddress":null,"id":31482,"landingOccurred":false,"latitude":7.1065565,"location":null,"logNumber":"CO-09032011-0018","longitude":-73.09968,"occurred":1313462220000,"potentialRelations":[],"rating":"Unrated","region":"Santander","reportedWeather":null,"shape":"Diamond","source":"MUFON","status":null,"submitted":1315103693000,"summary":"Glowing objects that apear in front of us an we take a photo","tags":["photo"],"timeZone":null,"timeZoneName":"","tweeted":0,"urls":["http://www.mufoncms.com/files_jeud8334j/31482_submitter_file1__Nikon5000207.JPG"],"weather":null,"zipcode":"0207","daysBetweenOccurrenceAndSubmission":18,"locationName":"Bucaramanga, Santander","triangle":false,"type":"UFO Sighting","$$hashKey":"object:37375"},{"address":null,"addressResolution":null,"altitude":"Unknown","city":"","country":"United States","county":null,"created":null,"deleted":false,"description":"","detailedDescription":"Was uploading photos taken this summer while on vacation and notice the object in the corner. at the time my wife was snapping photos of my children and i playing in the park near sea port village in downtown san diego across from the naval base. we did not notice anything in the sky that day, but later discovered it in the photo. thought it was interesting.","distance":"Unknown","duration":"","entityEncountered":false,"favorited":0,"features":"","flightPath":"","formattedAddress":null,"id":31481,"landingOccurred":false,"latitude":36.781211,"location":null,"logNumber":"US-09032011-0017","longitude":-119.4109024,"occurred":1309071600000,"potentialRelations":[],"rating":"Unrated","region":"California","reportedWeather":null,"shape":"Unknown","source":"MUFON","status":null,"submitted":1315102926000,"summary":"Object in downtown san diego","tags":["none"],"timeZone":null,"timeZoneName":"","tweeted":0,"urls":["http://www.mufoncms.com/files_jeud8334j/31481_submitter_file1__DSCN2812.jpg"],"weather":null,"zipcode":"0","daysBetweenOccurrenceAndSubmission":69,"locationName":"California","triangle":false,"type":"UFO Sighting","$$hashKey":"object:37376"},{"address":null,"addressResolution":null,"altitude":"Unknown","city":"Phoenix","country":"United States","county":null,"created":null,"deleted":false,"description":"","detailedDescription":"I had experienced other strange encounters in the past before this event took place. i had never really given much thought however to the past experiences. in 1991 i was with some friends swimming after dark at a nearby lake when we all witnessed several small flickering lights that danced above the surface of the water, and then instantly one by one shot straight into the air, disappearing from sight once they reached the height above the treeline in the distance. we all thought it might have been car lights reflecting on the water, or maybe someone in the woods with lights that were playing tricks on our eyes. we never really knew how to explain what we saw, we just knew we had seen it and it was enough to make us get out of the water. all we really knew was the objects resembled the actions of fireflies or lightning bugs but were moving and flashing at a higher rate of speed. and according to the distance across the lake from where we were, we all agreed they must have been about the size of baseballs or softballs. needless to say it wasn't something i would forget, but still questionable, or at least i thought it was at the time.\r\nthen, in 1995, i was talking with a friend outside of our church building. we saw what looked like 5 golden meteors, all different tail lengths, stream across the sky above us. their tails looked like amberish gold flakes or some sort of fiery golddust. again, kind of spooky to think of something that close to me, but i always thought it must have been meteors or something like that. we even entertained the thought that it would be really neat if they were angels! but without any proof we just chalked it up as something natural that we had witnessed.\r\nin '97 or '98, i can't be certain of the year, i was driving on an interstate that winds through a lot of trees. upon driving past a point where the trees clear for a bit, i was met by other drivers that had pulled over on the side of the shoulder. some were standing outside their vehicles and were pointing to an orb-like object hovering in mid-air approximately 2 or 3 miles from where we were. i pulled over behind one of the vehicles and got out myself. with my eye on the object, i made my way to the guy in front of me and asked \"what is that?\" he smiled, shook his his head and answered, \"you got me! but that lady 2 cars up said it's been there for about 5 minutes!\" it looked like a full moon, brightly lit, stationary, and spooky! well, before i could get too astonished at what i was observing, and before i could even question what the source of light could be, you know, large flare, spotlight on a plane or helicopter, it began to ascend slightly and very quickly started making distance from our line of sight. in seconds it was as if we all had pinhole vision and we were squinting to see it. like a star that suddenly quit emitting it's light, it was gone! i didn't even think of it at the time, but i should have exchanged phone numbers with some of the other witnesses while we talked on the side of the road. by the time i did think about it we had already disbursed from the area and were again back on the road. my apologies.\r\nnow, several years had passed before my next encounter. this encounter is what prompted me to make this report. i've thought about this for quite some time and finally decided it's time to share with the public this particular experience. okay, i'm sure by now most everyone has heard of the famous phoenix lights. if you haven't i would urge you to research it. it's quite interesting and i should note that before this experience i had never heard of the 1997 incident. \r\nmy son and i moved to phoenix shortly after my father passed away in '04. needing a change of pace after a brutal divorce, i took a job training sales associates for a company located in the center of the metroplex. we moved into a small 1 bedroom suite, enrolled him in school, and i started my new job the next day. our routine would last about year before we would seek a roommate with a larger space. a friend from church had a similar situation so we decided to join forces, and we moved into her garden apartment condo. fast forward to july 4th 2006.\r\nthe day was just like any other. i went to work that morning, got home around 4:30 pm and discussed briefly with my son on how his day went. we were preparing to let him spend the night with my roommates grandchild in scottsdale. after he left with them for the evening, my roommate and i discussed dinner plans. too tired to go out anywhere, and too hot to grill, we decided to cook inside and invite her daughter and fiance over.\r\nafter eating we all decided to retreat to the garden patio to visit. it was almost dark outside. the space within the patio area is approximately 12 ft. in width and 42 ft. in length with a 7 ft. wall that encompasses the area. on the west end is a gate that leads to a basketball court, and on the east end is a divider wall that seperates the neighbors patio area from ours. 3 ornamental orange trees lines the length of the south wall. although having larger canopies now, they are still there according to a google map i looked at today. we no longer live there so i'm not sure of any structural changes. google won't zoom down far enough to check it out, at least mine won't.\r\nanyway, the time was approximately 9:45-10:00 pm. my roommate had just stepped back in thru the sliding glass door to freshen a glass of tea. her daughter, fiance, and i were standing by the slider door talking when all of the sudden, something strange happened! starting at the west end gate and moving quickly across the patio floor, a shadow darkened the whole area, blocking out the reddish looking glow of smog and city lights overhead. we all stopped talking immediately and upon looking upward i almost fell to my knees. my roommates daughter gasped and her fiance darted torward the door but stopped to keep looking up. we thought the sky was falling! it scared the living daylights out of us! mesmerized, we just kept staring upward. immediately the air around us had changed. hearing a slight hum as the craft flew over us, the air felt really thick, and a sense of slow motion took over our bodies. i remember looking at each other, our mouths gaped open, eyes wide, utterly shocked. we all turned in the same direction the craft was flying, positioning ourselves to view it from that angle. my roommate was still inside freshening her tea and i remember hearing a couple of cubes tinkling the bottom of her glass. the kitchen window was open and her daughter called in to her saying \"mom get out here quick!\" still looking up, we observed the underbelly of the craft. the whole surface was wavy and shimmering kind of like water at night. there were no lights underneath as best as we could tell, but the surface was like that of mercury or some sort of liquid black metal. the underbelly stretched as far as we could see to the north above the roofline, and as far as we could see to the south on the other side of the block wall that runs the length of patio area. it was mega huge! if you google map the area between union hills and west bell road, you could get a fairly accurate estimate of the span. left wing tip union hills, right wing tip bell. after the craft passed over we observed the back end of the craft. this is how we know it was triangular in shape, much like a boomerang. the craft was outlined on top by an edge that inverted toward the center. it was also outlined on the bottom with the same inversion. the estimated space in between was about 30 to 40 ft. about as tall as a 2 story house. usually when i'm telling someone about this, i usually refer to 5 evenly spaced lights, but because of our field of projectory, it was impossible to see the far left side. we were however able to see 4 lights. the lights were blue-white in color and very bright. they were located directly between the outlines top and bottom and inverted toward the center. all the lights were the exact same size. two on the right, one in the center, and we assume two on the left although we could only see one.\r\nthe craft continued east very slowly until it left our field of sight. the whole encounter lasted approximately 1 minute. we were perplexed and amazed and spent the rest of the night talking about it until about 2:30 am. we talked about it often before my son and i decided to move back home. my roommate never did make it back outside in time to see it.\r\ni often think back to that night and wonder. who was piloting it? was it being piloted at all? how in the world was that thing staying in the air? and why would our government or anyone else's allow such a large craft to fly over the heads of so many people? obviously there exists a confidence that it's not going to crash. i still ponder it's origin. it doesn't seem like we should have technology that could produce such a machine, but then what do any of us really know?\r\nwell, i guess that's about it. i should tell you i haven't seen anything since that night. i'm not entirely sure i want to. but every now and then, after the sun goes down and the stars come out, i will sometimes go outside just to look up at the sky. i pray more now than i used to. not because of ufo's, but because i have had the opportunity to realize there are things that exist that are much bigger than me. i've learned to trust my creator. i've learned to study the bible and put to practice it's precepts. is there life on other planets? i don't know. while it seems arrogant on our part to dismiss the idea, i'm not sure i've understood why it would be all that necessary. at any rate, i guess god could do whatever he wants and if he wants et's then i'm sure he will have them. until we know for sure it's anybody's guess but i can say with confidence that i will never, ever forget that night.\r\nthanks and god bless!  \r\n     \r\n    \r\n","distance":"101-500 Feet","duration":"","entityEncountered":false,"favorited":0,"features":"Patterned Surface","flightPath":"Straight-line path","formattedAddress":null,"id":31480,"landingOccurred":false,"latitude":33.62764906733696,"location":null,"logNumber":"US-09032011-0016","longitude":-112.11628287963659,"occurred":1152074700000,"potentialRelations":[],"rating":"Unrated","region":"Arizona","reportedWeather":null,"shape":"Boomerang,   Triangle","source":"MUFON","status":null,"submitted":1315102505000,"summary":"My friends and i saw a large black triangle with large blue white lights on the back end of craft.","tags":["triangle","lights"],"timeZone":null,"timeZoneName":"","tweeted":0,"urls":null,"weather":null,"zipcode":"85023","daysBetweenOccurrenceAndSubmission":1886,"locationName":"Phoenix, Arizona","triangle":true,"type":"Black Triangle Sighting","$$hashKey":"object:37377"},{"address":null,"addressResolution":null,"altitude":"Over 500 Feet (under cloudcover)","city":"Everett","country":"United States","county":null,"created":null,"deleted":false,"description":"","detailedDescription":"I looked up at the night sky around 2:30 am on sep. 3rd 2011 and a shooting star caught my eye. then while i was standing in my back yard i looked to the south east wow i thought thats a bright star... so i watched this thing in the sky move slowly and as to hover and move around the sky bobing up and down.... it at first looks like just a bright star and ya think oh!!! thats the northern star.. ummm but it was south by south east hmmmm.... so i started to stair at it and it revealed some streaming lites out of the bottom of it like in a open to pointed shape all downword five of them.. it would glow brighter in a yellow white pink edges semi round starish shape and flash the tails of white blue green on and off slow not super fast or like a plain or helli, so also it was too close to be a star... i ran inside the house and got my cammera and started taking night shots of it.. then it hit me this is no star!!! so i wanted to flash a light at it as to get its attention maybe make it do somthing... a plan ran through my head and i jumped on top of my rack on my jeep with the cord of my hand held high powered 4000 watt plug in lite ran through the window and i pointed the lite at it and started flashinhg my lite on and off like morse code in mind to maybe get a reaction and all the while doin this at the craft... it moved i got excited and did it again it floated behind the top of a tree as to avoid my flashing it... then came out to one side of the tree adn for like an hour we seemed to flash back and forth at eachother... i realized at that moment it was not as far up as i thought but farther out in the skyline maybeee... duno??? but it would as it seems wait for me to flash back so i would wait different times to test it and it would wait too before flashing the streamers. i was verry drawn to this lite the longer you look at it it would like just freak ya out, ya wanna look away you feel weird kinda wanna rub ur eyes... ha! which trust me i did lots!!! it would flash five streamers out of the bottom and get bright then they went away. they seemed to grow out the bottom if that makes sense??? i stared leaving the lite on and circling the orb /star thing and it would bob move slightly get dimmer... then after about 30 minnutes of this game a flash of blue and red orbs slightly appart shot diagnal across the sky several hundred feet bellow the white yellow orb with streamers so fast i cant explain what the heck it was for anything... nothing we have in our world moves that fast!!! so now by this time i really wanna know what this orb/ star thing is at this point,now im thinkin milatery fly by was the red and blue orbs/ lites maybe??? duno???...  but this thing in the sky could make one side of the streamers go out and turn on the other side back and forth and could dimm itself so as to look smaller as if it was just a star in the sky .... i just two months ago got my eyes checked i have 20/20 vision!!! this was no star nothing i have ever seen before and not a helli or jet or plain or toy or ballon i watched it for two hours i cant say its not a space craft... if anyone is in disbalief i was at that very moment i just couldnt believe my eyes i watched it for hours thinking to myself no one will ever believe me.............     ","distance":"101-500 Feet","duration":"","entityEncountered":false,"favorited":0,"features":"","flightPath":"Hovering then path","formattedAddress":null,"id":31479,"landingOccurred":false,"latitude":47.98815191564743,"location":null,"logNumber":"US-09032011-0015","longitude":-122.2086135872705,"occurred":1315044000000,"potentialRelations":[],"rating":"Unrated","region":"Washington","reportedWeather":null,"shape":"Unknown","source":"MUFON","status":null,"submitted":1315096478000,"summary":"I flashed a high powered plug in car 4000 watt hand held lite at this star like thing much to close to be a star and the brightest star i have ever seen south by south east not the northern star it was no star!! no plain nothing that we as man have.","tags":["none"],"timeZone":null,"timeZoneName":"","tweeted":0,"urls":null,"weather":null,"zipcode":"98201","daysBetweenOccurrenceAndSubmission":0,"locationName":"Everett, Washington","triangle":false,"type":"UFO Sighting","$$hashKey":"object:37378"},{"address":null,"addressResolution":null,"altitude":"Treetop","city":"Elizabeth","country":"United States","county":null,"created":null,"deleted":false,"description":"","detailedDescription":"I was doing my friends hair in my apartment then took a break. for some reason i looked outside directly at the object. starred for about 10 secs and asked my client to also look at the object which soon disappeared in thin air after or acknowledgment. i knew right away it was a ufo. it floated in the air lightly rocking left to right.. disappeared.. then appeared again when i drew attention to my friend.. then disappeared after we starred. during the sighting i yelled omg jessica is that a ufo then she also looked out the window as well as i did to observe and then started tearing up at the eyes.. felt sick to my stomach during and after, so did my client..& still feel sick every time talking about it. i lost sight because it vanished. ","distance":"Unknown","duration":"","entityEncountered":false,"favorited":0,"features":"None","flightPath":"Other","formattedAddress":null,"id":31478,"landingOccurred":false,"latitude":40.654011016257236,"location":null,"logNumber":"US-09032011-0014","longitude":-74.25407607782206,"occurred":1315028400000,"potentialRelations":[],"rating":"Unrated","region":"New Jersey","reportedWeather":null,"shape":"Disc,   Saturn-like","source":"MUFON","status":null,"submitted":1315096431000,"summary":"Saucer shaped, floating with flashing red light, treetop level.. appear and disappear","tags":["flash","floating","light","saucer"],"timeZone":null,"timeZoneName":"","tweeted":0,"urls":null,"weather":null,"zipcode":"07208","daysBetweenOccurrenceAndSubmission":0,"locationName":"Elizabeth, New Jersey","triangle":false,"type":"UFO Sighting","$$hashKey":"object:37379"},{"address":null,"addressResolution":null,"altitude":"Over 500 Feet (no cloudcover)","city":"Lakeport","country":"United States","county":null,"created":null,"deleted":false,"description":"","detailedDescription":"On 09/02/11, between 2100 hrs. and 2115 hrs., my family and i were sitting in our backyard looking at the stars.  it was about a half hour after sunset and it was clear with no clouds.  we observed a round, orange colored, bright light traveling in the western sky over the cow mt. wilderness area.  it was traveling at a high rate of speed and was moving from the n/w towards the s/e.  even though it was dark where we were, i believe the sun was reflecting off of the object making it a bright orange color.  it traveled in a straight line as it continued across the sky.  when viewed through high powered binoculars the object appeared to be round.  as it continued s/e through the sky it dimmed to a light orange reddish color.\r\nthe speed of this object was incredible.  we lost sight of it as it went behind mt. konocti.  it's last trajectory was taking in the direction of the sacramento valley. we observed it for a total of about 4 minutes.\r\n\r\nbased on my experience of years of watching the night sky, i have never seen anything like this object before.  i have seen thousands of satellites, meteors, etc. in the sky and this object was not a satellite, meteor or plane.  the object appeared to be much lower and inside the atmosphere.  it made no sound and there were no flashing lights.  it left no trail behind it as it traveled through the sky. the object appeared to be holding the same elevation as it crossed the sky.\r\n\r\nwe were able take a picture of it with a cell phone. (see attached photo).  no stars are visible in the picture, indicating how bright the object was.  ","distance":"Over One Mile","duration":"","entityEncountered":false,"favorited":0,"features":"Unknown","flightPath":"Straight-line path","formattedAddress":null,"id":31477,"landingOccurred":false,"latitude":39.0467906,"location":null,"logNumber":"US-09032011-0013","longitude":-122.9129593,"occurred":1315023000000,"potentialRelations":[],"rating":"Unrated","region":"California","reportedWeather":null,"shape":"Circle","source":"MUFON","status":null,"submitted":1315087522000,"summary":"Orb","tags":["none"],"timeZone":null,"timeZoneName":"","tweeted":0,"urls":["http://www.mufoncms.com/files_jeud8334j/31477_submitter_file1__GetAttachment.jpg"],"weather":null,"zipcode":"95453","daysBetweenOccurrenceAndSubmission":0,"locationName":"Lakeport, California","triangle":false,"type":"UFO Sighting","$$hashKey":"object:37380"},{"address":null,"addressResolution":null,"altitude":"Unknown","city":"Barstow","country":"United States","county":null,"created":null,"deleted":false,"description":"","detailedDescription":"Please contact ","distance":"N/A","duration":"","entityEncountered":false,"favorited":0,"features":"None","flightPath":"Path with directional change,Other","formattedAddress":null,"id":31476,"landingOccurred":false,"latitude":35.0061717,"location":null,"logNumber":"US-09032011-0012","longitude":-116.9044926,"occurred":1142044200000,"potentialRelations":[],"rating":"Unrated","region":"California","reportedWeather":null,"shape":"Sphere","source":"MUFON","status":null,"submitted":1315086808000,"summary":"Us army . gun crew . orbs seen with flair systom on 25mm chain gun. engaged with lazer range finder . object reacted . returned with three others.","tags":["none"],"timeZone":null,"timeZoneName":"","tweeted":0,"urls":null,"weather":null,"zipcode":"0","daysBetweenOccurrenceAndSubmission":2002,"locationName":"Barstow, California","triangle":false,"type":"UFO Sighting","$$hashKey":"object:37381"},{"address":null,"addressResolution":null,"altitude":"Over 500 Feet (no cloudcover)","city":"Lodi","country":"United States","county":null,"created":null,"deleted":false,"description":"","detailedDescription":"On 9-1-2011 i woke at 11:45 to the dogs' furious barking.  after 5-6- minutes, i went to my west window to see what was causing them to bark.  about 20-25 degrees up i saw a red and yellow object. clearly visible were rows of alternating red and yellow lights in a circle formation, which was at least the size of my thumb.  after  perhaps 15 seconds it began to scintillate, with each light visibly twinkling.  i ran for my camera, and when i returned (approx. 10 seconds) the object had descended near to the western horizon.  i watched hoping it would reappear.  suddenly at a point nearly above my house two bright flashers appeared.  these flashers were like those emitted by strobe lights, bright white and much larger than a planes lights would be.  they vanished above my house toward the east.  ten seconds later another such light appeared - just suddenly popping into view in the middle of the sky.  followed in a few seconds by another, and another, until six had appeared and (presumably) went eastward.\r\ni went to my  kitchen window (east side of the house) and scanned the sky, but all i saw was venus and other stars.\r\nduring the time i observed these phenomena there was no sound and no other lights (like planes) visible.  air traffic at late night in this area is rare, and usually will be coming from the southeast as planes are making their landing approach to sacramento airport.","distance":"Over One Mile","duration":"","entityEncountered":false,"favorited":0,"features":"Unknown","flightPath":"Stationary","formattedAddress":null,"id":31475,"landingOccurred":false,"latitude":38.14359366608368,"location":null,"logNumber":"US-09032011-0011","longitude":-121.15629321251149,"occurred":1314860400000,"potentialRelations":[],"rating":"Unrated","region":"California","reportedWeather":null,"shape":"Circle,   Flash","source":"MUFON","status":null,"submitted":1315084771000,"summary":"Saw large colored light in sky followed by light flashes","tags":["landing","lights"],"timeZone":null,"timeZoneName":"","tweeted":0,"urls":null,"weather":null,"zipcode":"95240","daysBetweenOccurrenceAndSubmission":2,"locationName":"Lodi, California","triangle":false,"type":"UFO Sighting","$$hashKey":"object:37382"},{"address":null,"addressResolution":null,"altitude":"Unknown","city":"Manchester","country":"United States","county":null,"created":null,"deleted":false,"description":"","detailedDescription":"My fiance and i have been star gazing lately and we've noticed some phenomeneon we have never seen lately. from approximately 4:45am - 5:15am 9/3/2011 we witnessed what appeared to be a moving star traveling north, south and west. we witnessed this 5 times in 45 minutes. the first time we seen it heading north and it remained in our view for about a minute and 10 seconds. i ran in and checked the time soon after we lost sight of it as it traveled out of our sight, 4:48am. the second time we were in the front yard and my fiance seen a large ball of white light the size of a cantaloupe, shoot off south west, leavign a trail, when we witnessed the same star like object heading south this time. when she seen the huge white ball she choked. the third time we were in the back yard and we noticed a plane moving west, and as were observing that we noticed the star like object moving west, going out of sight. the 4th time we were on the back porch again hoping to see this, and we did as with the plane. the plane was heading west and the star like object was heading north again. i ran out to the front yard to try and keep this in sight and i saw (i assume the same object) heading south. i kept this in sight for about 2 minutes, watching it turn from the star like blue to a red, back to blue, red again until it went out of sight behind the tree lines. it seems like 3am - 5am is he best time to witness this lately.","distance":"Unknown","duration":"","entityEncountered":false,"favorited":0,"features":"None","flightPath":"Straight-line path,Path with directional change","formattedAddress":null,"id":31474,"landingOccurred":false,"latitude":35.47485450301959,"location":null,"logNumber":"US-09032011-0010","longitude":-86.10838031021383,"occurred":1315050300000,"potentialRelations":[],"rating":"Unrated","region":"Tennessee","reportedWeather":null,"shape":"Star-like","source":"MUFON","status":null,"submitted":1315059198000,"summary":"Moving star(s)","tags":["none"],"timeZone":null,"timeZoneName":"","tweeted":0,"urls":null,"weather":null,"zipcode":"37355","daysBetweenOccurrenceAndSubmission":0,"locationName":"Manchester, Tennessee","triangle":false,"type":"UFO Sighting","$$hashKey":"object:37383"},{"address":null,"addressResolution":null,"altitude":"Over 500 Feet (under cloudcover)","city":"Amsterdam","country":"The Netherlands","county":null,"created":null,"deleted":false,"description":"","detailedDescription":"Just so everyone knows i was never a believer until the other day when i saw something passing in the sky that was defiantly not a bird, plane, balloon, smudge on my camera, star or satellite it was a flying disk shaped vehicle. this did scare me quite a lot when i saw this as i just couldn't find any reasoning for what i was seeing.\r\n\r\nevery day i go onto my roof to feed my weed plants and on sunny days take some photos to show their growth. i was taking shots of the plants from below to make them look bigger, my cousin who was on the roof as well pointed something in the sky, at which point i looked above me to see 3 ufo's flying quite high above us and passing us not crazy speeds but still fast. straight away we looked at the photos taken on my computer so we could zoom in to see what they were. \r\n\r\nwell see for yourself and and get in contact if i am mistaken.\r\n\r\npeace out and keep watching the skys!","distance":"Over One Mile","duration":"00:00:12","entityEncountered":false,"favorited":0,"features":"Unknown","flightPath":"Straight-line path","formattedAddress":null,"id":31473,"landingOccurred":false,"latitude":52.3546579,"location":null,"logNumber":"NL-09032011-0009","longitude":4.8863756,"occurred":1315077780000,"potentialRelations":[],"rating":"Unrated","region":"Noord-Holland","reportedWeather":null,"shape":"Disc","source":"MUFON","status":null,"submitted":1315058459000,"summary":"Checking on my marijuana plants when something cruised above that was defiantly a ufo","tags":["ufo"],"timeZone":null,"timeZoneName":"","tweeted":0,"urls":["http://www.mufoncms.com/files_jeud8334j/31473_submitter_file1__DSC_0145.jpg"],"weather":null,"zipcode":"0","daysBetweenOccurrenceAndSubmission":-1,"locationName":"Amsterdam, Noord-Holland","triangle":false,"type":"UFO Sighting","$$hashKey":"object:37384"},{"address":null,"addressResolution":null,"altitude":"Unknown","city":"New York","country":"United States","county":null,"created":null,"deleted":false,"description":"","detailedDescription":"Sitting on my couch with a view out of my window, i saw a green streak of light faster than any shooting star and with much longer, green trail of light.  flew from west to east right over jfk airport.  streak remained for a few seconds.  i went to craigslist and made a post about the occurrence.  a reply from boston came within minutes.  someone saw the same thing.  a report i saw around august 31 on mufon's web page reminded me to post this occurrence. ","distance":"N/A","duration":"","entityEncountered":false,"favorited":0,"features":"Unknown","flightPath":"Straight-line path","formattedAddress":null,"id":31472,"landingOccurred":false,"latitude":40.6468028,"location":null,"logNumber":"US-09032011-0009","longitude":-73.8901861,"occurred":1186732800000,"potentialRelations":[],"rating":"Unrated","region":"New York","reportedWeather":null,"shape":"Unknown","source":"MUFON","status":null,"submitted":1315045348000,"summary":"Streak of green light from west horizon to east horizon over jfk airport.","tags":["ufo"],"timeZone":null,"timeZoneName":"","tweeted":0,"urls":null,"weather":null,"zipcode":"11236","daysBetweenOccurrenceAndSubmission":1485,"locationName":"New York, New York","triangle":false,"type":"UFO Sighting","$$hashKey":"object:37385"},{"address":null,"addressResolution":null,"altitude":"Over 500 Feet (no cloudcover)","city":"Modesto","country":"United States","county":null,"created":null,"deleted":false,"description":"","detailedDescription":"At 10:40 pm i witnessed a glowing orb high in the sky blinking read and green not in sequence another similar object 1 mile east in the sky at same elevation. ","distance":"501 Feet - 1 Mile","duration":"","entityEncountered":false,"favorited":0,"features":"None","flightPath":"Stationary","formattedAddress":null,"id":31471,"landingOccurred":false,"latitude":37.6407272,"location":null,"logNumber":"US-09032011-0008","longitude":-120.9888782,"occurred":1315028400000,"potentialRelations":[],"rating":"Unrated","region":"California","reportedWeather":null,"shape":"Circle","source":"MUFON","status":null,"submitted":1315040294000,"summary":"Blinking red and green orb seen high in the sky starlike but not","tags":["none"],"timeZone":null,"timeZoneName":"","tweeted":0,"urls":null,"weather":null,"zipcode":"95350","daysBetweenOccurrenceAndSubmission":0,"locationName":"Modesto, California","triangle":false,"type":"UFO Sighting","$$hashKey":"object:37386"},{"address":null,"addressResolution":null,"altitude":"Over 500 Feet (no cloudcover)","city":"Miami","country":"United States","county":null,"created":null,"deleted":false,"description":"","detailedDescription":"Multiple uafs/ufos flying over downtown miami on september 2, 2011.  \r\n\r\nlights / uafs / ufos were viewed over the bank of america building at roughly 11:20 pm.  at the time, we were sitting on our balcony of our building.  the two of us were speaking when an orb caught my eye, flying in a circle, disappearing and then reappearing.  i wore glass and thought maybe it was a reflection from my lens.  i asked \"hey, out of curiosity, do you see that behind you above the bank of america building?\" she quickly did see it   \r\n\r\nthere were multiple lights for about 5 minutes.  they would fly in circles and then spiral down and quickly shoot back up.  we viewed at least 2 to 3 at a time at one point.  at first, we tried recording / shooting photos on an iphone4 camera.  nothing came out.  we remembered that there was a camera in the bedroom so we ran in to grab it.  by the time we were recording, we only got about 40 seconds of footage and they were no longer spiraling down and back up again.  however, you can see in the video that they are circling, disappearing and reappearing.  \r\n\r\nunfortunately, the video quality is horrible compared to what we actually saw (kodak easyshare m380).  although they come up on the camera, they were actually much easier to see with the naked eye for the majority of the sighting.  also, although they appear to be blinking in the video at some points, the lights were never blinking; they remained solid, disappeared, and then reappeared seconds later.   \r\n\r\nas for what we thought the object was, we considered started discussing what we were seeing (the conclusions of our discussion is located below).  i try to keep an objective mind so i can't say what this was.  all i know is that there was something physical there and i've never seen anything like it before. \r\n\r\nsome facts to note: \r\n\r\nwe live 15 minutes from miami international.  however, this did not appear to be an airplane.  they did not maneuver like airplanes and moved to fast to be airplanes.  also, with this proximity to the airport, the airplanes fly extremely low to the ground both during takeoff and landing; these were too high to be taking off or landing aircraft.  further, we are pretty familiar with the flight paths both to and from the airport and this area was not part of the typical flight paths that we have previously witnessed.\r\n\r\nseparately, this seemed unlike any helicopter ive ever seen.  they seemed pretty high, did not make any noise, and did not have any blinking lights.  also, again, ive never seen a helicopter maneuver this fast or in the same fashion.\r\n\r\nadditionally, if these were helicopters/airplanes, they were flying extremely close together . . . probably too close under faa regulations (though i'm not 100% certain what those regs say). \r\n\r\nlast, in the video, there appears to be a spotlight pointed up into the sky, possibly from the bank of america building.  i do not believe the light was reflecting off of these uafs (they seemed to bright).  however, the moment they spotlight is shut off, the uafs disappear. \r\n\r\ni would be interested to know what miami international had on radar, if anything.\r\n\r\nif you require any further information, please contact me.\r\n","distance":"Over 1 Mile, Unknown","duration":"","entityEncountered":false,"favorited":0,"features":"Unknown","flightPath":"Hovering then path,Straight-line path,Path with directional change,Path then hovering,Other","formattedAddress":null,"id":31470,"landingOccurred":false,"latitude":25.757900837062277,"location":null,"logNumber":"US-09032011-0007","longitude":-80.18555568866144,"occurred":1315030800000,"potentialRelations":[],"rating":"Unrated","region":"Florida","reportedWeather":null,"shape":"Sphere","source":"MUFON","status":null,"submitted":1315039569000,"summary":"Multiple orbs flying in random directions then circuling and spiraling down, then shooting up.","tags":["none"],"timeZone":null,"timeZoneName":"","tweeted":0,"urls":["http://www.mufoncms.com/files_jeud8334j/31470_submitter_file1__sep2video.mov"],"weather":null,"zipcode":"33132","daysBetweenOccurrenceAndSubmission":0,"locationName":"Miami, Florida","triangle":false,"type":"UFO Sighting","$$hashKey":"object:37387"},{"address":null,"addressResolution":null,"altitude":"Unknown","city":"","country":"United States","county":null,"created":null,"deleted":false,"description":"","detailedDescription":"I want to know why no one at mufon has contacted me. i gave you reports of my sightings, and maybe abuctions. unless no one believes me. because it sounds to good to be true. i really need to talk to somone.  just because i have no solid proof. i can give you details. i can also give you a site ,where a ufo may have crashed . near where i live. i have been trying to talk to someone, ","distance":"Unknown","duration":"02:21:18","entityEncountered":false,"favorited":0,"features":"","flightPath":"","formattedAddress":null,"id":31469,"landingOccurred":false,"latitude":40.6341949,"location":null,"logNumber":"US-09032011-0006","longitude":-89.3913183,"occurred":551075400000,"potentialRelations":[],"rating":"Unrated","region":"Illinois","reportedWeather":null,"shape":"Unknown","source":"MUFON","status":null,"submitted":1315038769000,"summary":"Sightings","tags":["none"],"timeZone":null,"timeZoneName":"","tweeted":0,"urls":null,"weather":null,"zipcode":"0","daysBetweenOccurrenceAndSubmission":8842,"locationName":"Illinois","triangle":false,"type":"UFO Sighting","$$hashKey":"object:37388"},{"address":null,"addressResolution":null,"altitude":"Over 500 Feet (no cloudcover), Unknown","city":"Marietta","country":"United States","county":null,"created":null,"deleted":false,"description":"","detailedDescription":"On august 14 sun evening around 6:00pm i noticed a larger reflective object in a stationary position in the north /north/east sky. there were clouds of the very thin type and the object was just passing over them as they passed by the object. i went in to grab a kodak easy pic camera but was unable to locate the object with the camera, but |i could still see it visually. at this point i went back in the house to get my mothers 10x binoculars. it was a large translucent object that was starting a flight path from north/east to the south/west. the object was starting to gain a lot of altitude. i went back in to ask my dad to come have a look and when he found the object with the 10x binoculars he said it looked like a clover. i was surprised at his comment so when i looked again with the 10x binoculars it was three glowing round object / like a clover formation behind / beside the original object which reflected light in the beginning but was translucent through the 10x binoculars. this object was starting to gain a lot of altitude so my dad went back in the house and grabbed a 25x power binocular and the object was hard to locate but when i did find it it was really high way up there, still had the clover object with it. when i handed my dad the 25x power binocular to see he could not locate the object and when i turned my attention back to the sky it was no longer there. i was sure it had climbed to such a height we could no longer see it.\r\n\r\nit was 6:30pm at when we gave up. but there is a lot of air traffic here from the atl heartsfield air port as well as dobbins afb which is close. i did not see any f22 ect check out the object but it was really high, higher then the cloud cover to begin with then it ascended to a extreme height.\r\n\r\nthe object was not a plane or helicopter. and guessing from the height and the viewable size it had to have been really large, even my dad comment whatever it is it is big. way bigger then any weather balloon or birthday balloon.\r\n\r\nsurely this was observed by other people through out this area.\r\n\r\nthe height can be figured by the cloud cover this day as the object was just over the passing clouds when first seeing it.","distance":"Unknown","duration":"","entityEncountered":false,"favorited":0,"features":"Unknown","flightPath":"Stationary,Hovering then path","formattedAddress":null,"id":31468,"landingOccurred":false,"latitude":34.0177256716955,"location":null,"logNumber":"US-09032011-0005","longitude":-84.50934925476321,"occurred":1313370000000,"potentialRelations":[],"rating":"Unrated","region":"Georgia","reportedWeather":null,"shape":"Sphere,   Other","source":"MUFON","status":null,"submitted":1315036244000,"summary":"A reflective object but when looking through binoculars it appeared translucent then later at a higher altitude it had three glowing / gold objects forming like a clover beside / beneth it.","tags":["none"],"timeZone":null,"timeZoneName":"","tweeted":0,"urls":null,"weather":null,"zipcode":"30066","daysBetweenOccurrenceAndSubmission":19,"locationName":"Marietta, Georgia","triangle":false,"type":"UFO Sighting","$$hashKey":"object:37389"},{"address":null,"addressResolution":null,"altitude":"Landed","city":"Center","country":"United States","county":null,"created":null,"deleted":false,"description":"","detailedDescription":"I was a senior in high school.  it was 10:30pm.  my mother went outside to throw left over food over the fence for the racoons.  i heard her scream my name.  i went outside near the fence and she pointed east and yelled, \"look!\"\r\n\r\nthere was a disk shaped object about 100 yards away hovering above the tree line on the other side of a large open field.  it was the size of a football stadium.  biggest thing i've ever seen.  there were a few lights along the lower half of the object.  the appearance of the object was black.  i could see a single row of windows along the edge.\r\n\r\nthe object dropped behind the tree line and landed.  we could see the lights through the trees.  it then rose back up silently above the tree line again.\r\n\r\nit then took off at an incredible rate of speed along our line of sight.  so it appeared like it just disappeared.\r\n\r\nwe went back inside and realized that much time had passed.  when i went out side the tv show nightline was on.  it started around 10:30pm.  when we came back in it was 2:00am and we don't know why so much time passed.\r\n\r\nwe went into separate rooms and drew pictures of the object which i still have today.\r\n\r\nthis is the first time i've told anyone about this except for my wife.\r\n","distance":"101-500 Feet","duration":"01:00:00","entityEncountered":false,"favorited":0,"features":"Window(s)","flightPath":"Hovering then path","formattedAddress":null,"id":31467,"landingOccurred":true,"latitude":31.727304899178908,"location":null,"logNumber":"US-09032011-0004","longitude":-94.26914604876778,"occurred":497941200000,"potentialRelations":[],"rating":"Unrated","region":"Texas","reportedWeather":null,"shape":"Other","source":"MUFON","status":null,"submitted":1315034892000,"summary":"Enormous disk like object with lights hovered over tree line.  dipped belowe tree line and landed.  rose up, hovered and left at high rate of speed.","tags":["lights"],"timeZone":null,"timeZoneName":"","tweeted":0,"urls":null,"weather":null,"zipcode":"75935","daysBetweenOccurrenceAndSubmission":9457,"locationName":"Center, Texas","triangle":false,"type":"UFO Landing","$$hashKey":"object:37390"},{"address":null,"addressResolution":null,"altitude":"Unknown","city":"Albany","country":"United States","county":null,"created":null,"deleted":false,"description":"","detailedDescription":"This is the second time we have wittnessed this object. first time was in july 2010 just south of due west. it lasted for about two hours and we saw a small white object fly past at hight speed in a upward direction.I figured it was a weird star\r\nand a meteor passing at a strange angle. i contacted a friend that works for a local news station to see if anyone else reported anything strange.\r\nhe told me they had no reports. so i left it at that.\r\n\r\nmy stepson who was with me the first time we saw it, told me he had seen it a few more times. i really did not bother to look, and laughed it off still believing it was just a strange star. \r\n\r\n\r\nthe second time was tonight (9/2/11) 10:30pm about an hour ago.\r\naporx 30 to 40 degrees north of due west. same flashing, stationary lights, but when a plane passed near , it dissapeared. 5 min later it was back. \r\n\r\ni just went out to look again at 12:02 am in is now in the east sky aprox 50 degrees north of east..\r\n\r\ni did not see it move position, and no other star in the sky looks like it!\r\n\r\n\r\nthis is happening now!!!\r\n\r\ni filmed the object...At 12:20 am ....It's not a star , or a plane...\r\n\r\nit is now out of view below the horizon in the east!\r\n\r\n\r\n\r\n\r\n","distance":"Unknown","duration":"","entityEncountered":false,"favorited":0,"features":"None","flightPath":"Stationary","formattedAddress":null,"id":31466,"landingOccurred":false,"latitude":42.6597093,"location":null,"logNumber":"US-09032011-0003","longitude":-73.7507317,"occurred":1315028100000,"potentialRelations":[],"rating":"Unrated","region":"New York","reportedWeather":null,"shape":"Flash,   Sphere,   Star-like,   Other","source":"MUFON","status":null,"submitted":1315034889000,"summary":"Stationary pulsating lights(red on bottom, green on top, mixed blue, yellow, white)  small white object fly by ( up direction)","tags":["lights"],"timeZone":null,"timeZoneName":"","tweeted":0,"urls":null,"weather":null,"zipcode":"12123","daysBetweenOccurrenceAndSubmission":0,"locationName":"Albany, New York","triangle":false,"type":"UFO Sighting","$$hashKey":"object:37391"},{"address":null,"addressResolution":null,"altitude":"Over 500 Feet (under cloudcover)","city":"Dyer","country":"United States","county":null,"created":null,"deleted":false,"description":"","detailedDescription":"In early april my huband and i were looking out the window and noticed a ufo and then we realized there were several of them. we saw a group of ufo's in the sky across the street from our home. i noticed it because it was out of place in the sky and i realized it was a ufo. we immediately got our digital camera and started taking a series of 15 pictures. the ufo's were in a sort of straight but diagonal line, there were 4 of them. 3 were in a line and one was off to the left side. we watched them sort of moving in and out of the clouds or changing shape and slowly descending in unison. they were very reflective of the setting sun.They moved in unison the whole time, and when the event was over the blended in with the clouds and disappeared. the whole thing lasted a bit more than 5 minutes. the series of pictures in a row shows hte movement of the objects. the helicopter was too far away to hear it, or to tell if it was a black heliecopter or not. we were excited but remained calm and had no further issues resulting from the event. we did not write down the date, time, or our observations at that time.","distance":"501 Feet - 1 Mile","duration":"","entityEncountered":false,"favorited":0,"features":"None","flightPath":"Path then hovering","formattedAddress":null,"id":31465,"landingOccurred":false,"latitude":41.48520131337795,"location":null,"logNumber":"US-09032011-0002","longitude":-87.52543025727122,"occurred":1301794200000,"potentialRelations":[],"rating":"Unrated","region":"Indiana","reportedWeather":null,"shape":"Other","source":"MUFON","status":null,"submitted":1315034331000,"summary":"Reflective hatch mark -like group of 4 ufo's","tags":["ufo"],"timeZone":null,"timeZoneName":"","tweeted":0,"urls":["http://www.mufoncms.com/files_jeud8334j/31465_submitter_file1__1.jpg","http://www.mufoncms.com/files_jeud8334j/31465_submitter_file2__7.jpg","http://www.mufoncms.com/files_jeud8334j/31465_submitter_file3__10.jpg"],"weather":null,"zipcode":"46311","daysBetweenOccurrenceAndSubmission":153,"locationName":"Dyer, Indiana","triangle":false,"type":"UFO Sighting","$$hashKey":"object:37392"}],"last":false,"totalElements":82758,"totalPages":2759,"sort":[{"direction":"DESC","property":"_id","ignoreCase":false,"nullHandling":"NATIVE","ascending":false}],"first":false,"numberOfElements":30,"size":30,"number":1793}
